setup.py
envopt/__init__.py
envopt/envopt.py
envopt.egg-info/PKG-INFO
envopt.egg-info/SOURCES.txt
envopt.egg-info/dependency_links.txt
envopt.egg-info/requires.txt
envopt.egg-info/top_level.txt